Workbook
Name Slicer_Category: #N/A
Name Slicer_Has_Duplicate_ID: #N/A
Name Slicer_Status: #N/A

Sheet Summary
B2: Audit Reconciliation — Summary
B3: General Ledger vs Bank Statement · sve KPI vrijednosti su formule vezane na sheet 'Reconciliation' i azuriraju se automatski
B4: ="Report generated: "&TEXT(TODAY(),"DD.MM.YYYY")
B6: Total Transactions | D6: Matched | F6: Exceptions | H6: Duplicates
B7: =COUNTA(Reconciliation!$A$2:$A$996) | D7: =COUNTIF(Reconciliation!$M$2:$M$996,"Matched") | F7: =COUNTIF(Reconciliation!$N$2:$N$996,"Yes") | H7: =COUNTIF(Reconciliation!$O$2:$O$996,"Yes")
B10: Only in GL | D10: Only in Bank | F10: Amount Mismatch | H10: Match Rate
B11: =COUNTIF(Reconciliation!$M$2:$M$996,"Only in GL") | D11: =COUNTIF(Reconciliation!$M$2:$M$996,"Only in Bank") | F11: =COUNTIF(Reconciliation!$M$2:$M$996,"Amount Mismatch") | H11: =IFERROR(COUNTIF(Reconciliation!$M$2:$M$996,"Matched")/COUNTA(Reconciliation!$A$2:$A$996),0)
B14: Exception Value | D14: Above Materiality | F14: Largest Exception | H14: Avg Exception
B15: =SUMIF(Reconciliation!$N$2:$N$996,"Yes",Reconciliation!$K$2:$K$996) | D15: =COUNTIFS(Reconciliation!$N$2:$N$996,"Yes",Reconciliation!$K$2:$K$996,">"&$B$18) | F15: =SUMPRODUCT(MAX((Reconciliation!$N$2:$N$996="Yes")*Reconciliation!$K$2:$K$996)) | H15: =IFERROR(SUMIF(Reconciliation!$N$2:$N$996,"Yes",Reconciliation!$K$2:$K$996)/COUNTIF(Reconciliation!$N$2:$N$996,"Yes"),0)
B17: Materiality Threshold (KM) | D17: ← plava brojka je jedina celija koju rucno mijenjas; KPI 'Above Materiality' i kolona N na 'Exceptions' se preracunavaju same
B18: 1000
B21: Breakdown po statusu
B22: Status | C22: Transactions | D22: % of Total | E22: Net Amount | F22: Absolute Value
B23: Matched | C23: =COUNTIF(Reconciliation!$M$2:$M$996,$B23) | D23: =IFERROR($C23/COUNTA(Reconciliation!$A$2:$A$996),0) | E23: =SUMIF(Reconciliation!$M$2:$M$996,$B23,Reconciliation!$J$2:$J$996) | F23: =SUMIF(Reconciliation!$M$2:$M$996,$B23,Reconciliation!$K$2:$K$996)
B24: Only in GL | C24: =COUNTIF(Reconciliation!$M$2:$M$996,$B24) | D24: =IFERROR($C24/COUNTA(Reconciliation!$A$2:$A$996),0) | E24: =SUMIF(Reconciliation!$M$2:$M$996,$B24,Reconciliation!$J$2:$J$996) | F24: =SUMIF(Reconciliation!$M$2:$M$996,$B24,Reconciliation!$K$2:$K$996)
B25: Only in Bank | C25: =COUNTIF(Reconciliation!$M$2:$M$996,$B25) | D25: =IFERROR($C25/COUNTA(Reconciliation!$A$2:$A$996),0) | E25: =SUMIF(Reconciliation!$M$2:$M$996,$B25,Reconciliation!$J$2:$J$996) | F25: =SUMIF(Reconciliation!$M$2:$M$996,$B25,Reconciliation!$K$2:$K$996)
B26: Amount Mismatch | C26: =COUNTIF(Reconciliation!$M$2:$M$996,$B26) | D26: =IFERROR($C26/COUNTA(Reconciliation!$A$2:$A$996),0) | E26: =SUMIF(Reconciliation!$M$2:$M$996,$B26,Reconciliation!$J$2:$J$996) | F26: =SUMIF(Reconciliation!$M$2:$M$996,$B26,Reconciliation!$K$2:$K$996)
B27: TOTAL | C27: =SUM(C23:C26) | D27: =SUM(D23:D26) | E27: =SUM(E23:E26) | F27: =SUM(F23:F26)
B30: Napomene / pretpostavke
B31: • Podaci su sinteticki (generisani u Pythonu, seed=42) — nisu stvarne transakcije.
B32: • Merge je radjen po Transaction_ID (outer join). Prije merge-a je svaka tabela de-duplicirana (keep='first') da jedan ID daje jedan red.
B33: • Amount Mismatch = |Amount_GL - Amount_Bank| > 0.01 (tolerancija na zaokruzivanje).
B34: • 'Duplicates' broji jedinstvene Transaction_ID-eve koji se pojavljuju vise od jednom u GL ili Bank tabeli.
B35: • Bank Statement nema Category/Account — bank-only redovi su oznaceni kao 'Unclassified (Bank only)'.
B36: • Datumi u banci su 0-3 dana kasniji od GL (clearing delay); to nije tretirano kao izuzetak.
B37: • Materiality threshold (1000 KM u celiji B18) je proizvoljno postavljen za demonstraciju — u stvarnoj reviziji izvodi se iz ukupnog prometa ili bilansne sume.
B38: • 'Absolute Value' koristi Abs_Amount da se prihodi i troskovi medjusobno ne ponistavaju.

Sheet Exceptions
A1: Transaction_ID | B1: Date | C1: Category | D1: Account | E1: Description_GL | F1: Description_Bank | G1: Amount_GL | H1: Amount_Bank | I1: Amount | J1: Abs_Amount | K1: Amount_Diff | L1: Abs_Diff | M1: Status | N1: Above_Materiality | O1: Priority | P1: Assigned_To | Q1: Resolution_Notes | R1: Resolved
A2: TXN-00376 | B2: 45360 | C2: Sales Revenue | D2: 4000 | E2: Invoice payment received | F2: INVOICE PAYMENT RECEIV | G2: 18808.11 | H2: 188081.1 | I2: 18808.11 | J2: 18808.11 | K2: -169272.99 | L2: =IFERROR(ABS(K2),"") | M2: Amount Mismatch | N2: =IF(J2>Summary!$B$18,"Yes","No") | O2: =RANK(J2,$J$2:$J$64,0)
A3: TXN-00120 | B3: 45295 | C3: Vendor Payment | D3: 5100 | E3: Contractor fee | F3: CONTRACTOR FEE | G3: -14882.22 | H3: -148822.2 | I3: -14882.22 | J3: 14882.22 | K3: 133939.98 | L3: =IFERROR(ABS(K3),"") | M3: Amount Mismatch | N3: =IF(J3>Summary!$B$18,"Yes","No") | O3: =RANK(J3,$J$2:$J$64,0)
A4: TXN-09008 | B4: 45417 | C4: Vendor Payment | D4: 5100 | E4: Contractor fee | G4: -14623.94 | I4: -14623.94 | J4: 14623.94 | L4: =IFERROR(ABS(K4),"") | M4: Only in GL | N4: =IF(J4>Summary!$B$18,"Yes","No") | O4: =RANK(J4,$J$2:$J$64,0)
A5: TXN-09013 | B5: 45295 | C5: Vendor Payment | D5: 5100 | E5: Supplier invoice | G5: -13985.64 | I5: -13985.64 | J5: 13985.64 | L5: =IFERROR(ABS(K5),"") | M5: Only in GL | N5: =IF(J5>Summary!$B$18,"Yes","No") | O5: =RANK(J5,$J$2:$J$64,0)
A6: TXN-00670 | B6: 45653 | C6: Vendor Payment | D6: 5100 | E6: Contractor fee | F6: CONTRACTOR FEE | G6: -13607.35 | H6: -13.6 | I6: -13607.35 | J6: 13607.35 | K6: -13593.75 | L6: =IFERROR(ABS(K6),"") | M6: Amount Mismatch | N6: =IF(J6>Summary!$B$18,"Yes","No") | O6: =RANK(J6,$J$2:$J$64,0)
A7: TXN-09001 | B7: 45308 | C7: Vendor Payment | D7: 5100 | E7: Vendor payment - materials | G7: -11925.61 | I7: -11925.61 | J7: 11925.61 | L7: =IFERROR(ABS(K7),"") | M7: Only in GL | N7: =IF(J7>Summary!$B$18,"Yes","No") | O7: =RANK(J7,$J$2:$J$64,0)
A8: TXN-09020 | B8: 45436 | C8: Vendor Payment | D8: 5100 | E8: Contractor fee | G8: -11408.77 | I8: -11408.77 | J8: 11408.77 | L8: =IFERROR(ABS(K8),"") | M8: Only in GL | N8: =IF(J8>Summary!$B$18,"Yes","No") | O8: =RANK(J8,$J$2:$J$64,0)
A9: TXN-09002 | B9: 45414 | C9: Vendor Payment | D9: 5100 | E9: Vendor payment - materials | G9: -11345.48 | I9: -11345.48 | J9: 11345.48 | L9: =IFERROR(ABS(K9),"") | M9: Only in GL | N9: =IF(J9>Summary!$B$18,"Yes","No") | O9: =RANK(J9,$J$2:$J$64,0)
A10: TXN-00583 | B10: 45632 | C10: Vendor Payment | D10: 5100 | E10: Vendor payment - materials | F10: VENDOR PAYMENT - MATER | G10: -11115.22 | H10: -11490.6 | I10: -11115.22 | J10: 11115.22 | K10: 375.38 | L10: =IFERROR(ABS(K10),"") | M10: Amount Mismatch | N10: =IF(J10>Summary!$B$18,"Yes","No") | O10: =RANK(J10,$J$2:$J$64,0)
A11: TXN-09021 | B11: 45361 | C11: Vendor Payment | D11: 5100 | E11: Supplier invoice | G11: -10831.59 | I11: -10831.59 | J11: 10831.59 | L11: =IFERROR(ABS(K11),"") | M11: Only in GL | N11: =IF(J11>Summary!$B$18,"Yes","No") | O11: =RANK(J11,$J$2:$J$64,0)
A12: TXN-09023 | B12: 45337 | C12: Vendor Payment | D12: 5100 | E12: Vendor payment - materials | G12: -10519.65 | I12: -10519.65 | J12: 10519.65 | L12: =IFERROR(ABS(K12),"") | M12: Only in GL | N12: =IF(J12>Summary!$B$18,"Yes","No") | O12: =RANK(J12,$J$2:$J$64,0)
A13: TXN-09025 | B13: 45494 | C13: Vendor Payment | D13: 5100 | E13: Supplier invoice | G13: -10032.3 | I13: -10032.3 | J13: 10032.3 | L13: =IFERROR(ABS(K13),"") | M13: Only in GL | N13: =IF(J13>Summary!$B$18,"Yes","No") | O13: =RANK(J13,$J$2:$J$64,0)
A14: TXN-09019 | B14: 45386 | C14: Vendor Payment | D14: 5100 | E14: Supplier invoice | G14: -9548.1 | I14: -9548.1 | J14: 9548.1 | L14: =IFERROR(ABS(K14),"") | M14: Only in GL | N14: =IF(J14>Summary!$B$18,"Yes","No") | O14: =RANK(J14,$J$2:$J$64,0)
A15: TXN-09015 | B15: 45509 | C15: Payroll | D15: 6000 | E15: Monthly salary run | G15: -9535.87 | I15: -9535.87 | J15: 9535.87 | L15: =IFERROR(ABS(K15),"") | M15: Only in GL | N15: =IF(J15>Summary!$B$18,"Yes","No") | O15: =RANK(J15,$J$2:$J$64,0)
A16: TXN-09017 | B16: 45653 | C16: Payroll | D16: 6000 | E16: Monthly salary run | G16: -9119.86 | I16: -9119.86 | J16: 9119.86 | L16: =IFERROR(ABS(K16),"") | M16: Only in GL | N16: =IF(J16>Summary!$B$18,"Yes","No") | O16: =RANK(J16,$J$2:$J$64,0)
A17: TXN-09007 | B17: 45508 | C17: Payroll | D17: 6000 | E17: Payroll transfer | G17: -8659.91 | I17: -8659.91 | J17: 8659.91 | L17: =IFERROR(ABS(K17),"") | M17: Only in GL | N17: =IF(J17>Summary!$B$18,"Yes","No") | O17: =RANK(J17,$J$2:$J$64,0)
A18: TXN-09009 | B18: 45567 | C18: Payroll | D18: 6000 | E18: Payroll transfer | G18: -7143.09 | I18: -7143.09 | J18: 7143.09 | L18: =IFERROR(ABS(K18),"") | M18: Only in GL | N18: =IF(J18>Summary!$B$18,"Yes","No") | O18: =RANK(J18,$J$2:$J$64,0)
A19: TXN-00206 | B19: 45506 | C19: Payroll | D19: 6000 | E19: Employee wages | F19: EMPLOYEE WAGES | G19: -7023.64 | H19: -70.23 | I19: -7023.64 | J19: 7023.64 | K19: -6953.41 | L19: =IFERROR(ABS(K19),"") | M19: Amount Mismatch | N19: =IF(J19>Summary!$B$18,"Yes","No") | O19: =RANK(J19,$J$2:$J$64,0)
A20: TXN-00616 | B20: 45457 | C20: Rent | D20: 6100 | E20: Warehouse lease | F20: WAREHOUSE LEASE | G20: -5922.24 | H20: -5971.2 | I20: -5922.24 | J20: 5922.24 | K20: 48.96 | L20: =IFERROR(ABS(K20),"") | M20: Amount Mismatch | N20: =IF(J20>Summary!$B$18,"Yes","No") | O20: =RANK(J20,$J$2:$J$64,0)
A21: TXN-09024 | B21: 45434 | C21: Rent | D21: 6100 | E21: Monthly office rent | G21: -5776.25 | I21: -5776.25 | J21: 5776.25 | L21: =IFERROR(ABS(K21),"") | M21: Only in GL | N21: =IF(J21>Summary!$B$18,"Yes","No") | O21: =RANK(J21,$J$2:$J$64,0)
A22: TXN-09003 | B22: 45565 | C22: Rent | D22: 6100 | E22: Warehouse lease | G22: -4990.02 | I22: -4990.02 | J22: 4990.02 | L22: =IFERROR(ABS(K22),"") | M22: Only in GL | N22: =IF(J22>Summary!$B$18,"Yes","No") | O22: =RANK(J22,$J$2:$J$64,0)
A23: TXN-09006 | B23: 45602 | C23: Payroll | D23: 6000 | E23: Payroll transfer | G23: -4962.75 | I23: -4962.75 | J23: 4962.75 | L23: =IFERROR(ABS(K23),"") | M23: Only in GL | N23: =IF(J23>Summary!$B$18,"Yes","No") | O23: =RANK(J23,$J$2:$J$64,0)
A24: TXN-09005 | B24: 45318 | C24: Vendor Payment | D24: 5100 | E24: Vendor payment - materials | G24: -4601.7 | I24: -4601.7 | J24: 4601.7 | L24: =IFERROR(ABS(K24),"") | M24: Only in GL | N24: =IF(J24>Summary!$B$18,"Yes","No") | O24: =RANK(J24,$J$2:$J$64,0)
A25: TXN-09022 | B25: 45475 | C25: Rent | D25: 6100 | E25: Rent payment | G25: -3848.12 | I25: -3848.12 | J25: 3848.12 | L25: =IFERROR(ABS(K25),"") | M25: Only in GL | N25: =IF(J25>Summary!$B$18,"Yes","No") | O25: =RANK(J25,$J$2:$J$64,0)
A26: TXN-09012 | B26: 45496 | C26: Rent | D26: 6100 | E26: Monthly office rent | G26: -3543.71 | I26: -3543.71 | J26: 3543.71 | L26: =IFERROR(ABS(K26),"") | M26: Only in GL | N26: =IF(J26>Summary!$B$18,"Yes","No") | O26: =RANK(J26,$J$2:$J$64,0)
A27: TXN-09010 | B27: 45600 | C27: Rent | D27: 6100 | E27: Warehouse lease | G27: -3333 | I27: -3333 | J27: 3333 | L27: =IFERROR(ABS(K27),"") | M27: Only in GL | N27: =IF(J27>Summary!$B$18,"Yes","No") | O27: =RANK(J27,$J$2:$J$64,0)
A28: TXN-00789 | B28: 45293 | C28: Travel & Entertainment | D28: 6400 | E28: Client dinner | F28: CLIENT DINNER | G28: -3255.56 | H28: -32555.6 | I28: -3255.56 | J28: 3255.56 | K28: 29300.04 | L28: =IFERROR(ABS(K28),"") | M28: Amount Mismatch | N28: =IF(J28>Summary!$B$18,"Yes","No") | O28: =RANK(J28,$J$2:$J$64,0)
A29: TXN-09004 | B29: 45330 | C29: Rent | D29: 6100 | E29: Rent payment | G29: -2085.79 | I29: -2085.79 | J29: 2085.79 | L29: =IFERROR(ABS(K29),"") | M29: Only in GL | N29: =IF(J29>Summary!$B$18,"Yes","No") | O29: =RANK(J29,$J$2:$J$64,0)
A30: TXN-09014 | B30: 45403 | C30: Vendor Payment | D30: 5100 | E30: Supplier invoice | G30: -2032.89 | I30: -2032.89 | J30: 2032.89 | L30: =IFERROR(ABS(K30),"") | M30: Only in GL | N30: =IF(J30>Summary!$B$18,"Yes","No") | O30: =RANK(J30,$J$2:$J$64,0)
A31: TXN-09011 | B31: 45423 | C31: Rent | D31: 6100 | E31: Warehouse lease | G31: -2030.85 | I31: -2030.85 | J31: 2030.85 | L31: =IFERROR(ABS(K31),"") | M31: Only in GL | N31: =IF(J31>Summary!$B$18,"Yes","No") | O31: =RANK(J31,$J$2:$J$64,0)
A32: TXN-00641 | B32: 45560 | C32: Rent | D32: 6100 | E32: Monthly office rent | F32: MONTHLY OFFICE RENT | G32: -1728.74 | H32: -1316.02 | I32: -1728.74 | J32: 1728.74 | K32: -412.72 | L32: =IFERROR(ABS(K32),"") | M32: Amount Mismatch | N32: =IF(J32>Summary!$B$18,"Yes","No") | O32: =RANK(J32,$J$2:$J$64,0)
A33: TXN-09016 | B33: 45363 | C33: Vendor Payment | D33: 5100 | E33: Supplier invoice | G33: -1634.63 | I33: -1634.63 | J33: 1634.63 | L33: =IFERROR(ABS(K33),"") | M33: Only in GL | N33: =IF(J33>Summary!$B$18,"Yes","No") | O33: =RANK(J33,$J$2:$J$64,0)
A34: TXN-09018 | B34: 45646 | C34: Vendor Payment | D34: 5100 | E34: Contractor fee | G34: -1215.59 | I34: -1215.59 | J34: 1215.59 | L34: =IFERROR(ABS(K34),"") | M34: Only in GL | N34: =IF(J34>Summary!$B$18,"Yes","No") | O34: =RANK(J34,$J$2:$J$64,0)
A35: TXN-00245 | B35: 45483 | C35: Rent | D35: 6100 | E35: Rent payment | F35: RENT PAYMENT | G35: -937.97 | H35: -93.79 | I35: -937.97 | J35: 937.97 | K35: -844.18 | L35: =IFERROR(ABS(K35),"") | M35: Amount Mismatch | N35: =IF(J35>Summary!$B$18,"Yes","No") | O35: =RANK(J35,$J$2:$J$64,0)
A36: TXN-00871 | B36: 45406 | C36: Office Supplies | D36: 6300 | E36: Stationery purchase | F36: STATIONERY PURCHASE | G36: -820.62 | H36: -521.53 | I36: -820.62 | J36: 820.62 | K36: -299.09 | L36: =IFERROR(ABS(K36),"") | M36: Amount Mismatch | N36: =IF(J36>Summary!$B$18,"Yes","No") | O36: =RANK(J36,$J$2:$J$64,0)
A37: TXN-00770 | B37: 45480 | C37: Utilities | D37: 6200 | E37: Internet & telecom | F37: INTERNET & TELECOM | G37: -747.51 | H37: -689.45 | I37: -747.51 | J37: 747.51 | K37: -58.06 | L37: =IFERROR(ABS(K37),"") | M37: Amount Mismatch | N37: =IF(J37>Summary!$B$18,"Yes","No") | O37: =RANK(J37,$J$2:$J$64,0)
A38: TXN-00876 | B38: 45621 | C38: Travel & Entertainment | D38: 6400 | E38: Hotel accommodation | F38: HOTEL ACCOMMODATION | G38: -397.33 | H38: -284.39 | I38: -397.33 | J38: 397.33 | K38: -112.94 | L38: =IFERROR(ABS(K38),"") | M38: Amount Mismatch | N38: =IF(J38>Summary!$B$18,"Yes","No") | O38: =RANK(J38,$J$2:$J$64,0)
A39: TXN-00677 | B39: 45502 | C39: Travel & Entertainment | D39: 6400 | E39: Client dinner | F39: CLIENT DINNER | G39: -336.56 | H39: -3365.6 | I39: -336.56 | J39: 336.56 | K39: 3029.04 | L39: =IFERROR(ABS(K39),"") | M39: Amount Mismatch | N39: =IF(J39>Summary!$B$18,"Yes","No") | O39: =RANK(J39,$J$2:$J$64,0)
A40: TXN-09507 | B40: 45533 | C40: Unclassified (Bank only) | F40: INTEREST ACCRUAL | H40: 239.42 | I40: 239.42 | J40: 239.42 | L40: =IFERROR(ABS(K40),"") | M40: Only in Bank | N40: =IF(J40>Summary!$B$18,"Yes","No") | O40: =RANK(J40,$J$2:$J$64,0)
A41: TXN-09504 | B41: 45568 | C41: Unclassified (Bank only) | F41: DEPOSIT INTEREST CREDI | H41: 238.95 | I41: 238.95 | J41: 238.95 | L41: =IFERROR(ABS(K41),"") | M41: Only in Bank | N41: =IF(J41>Summary!$B$18,"Yes","No") | O41: =RANK(J41,$J$2:$J$64,0)
A42: TXN-00183 | B42: 45581 | C42: Office Supplies | D42: 6300 | E42: Office equipment | F42: OFFICE EQUIPMENT | G42: -171.33 | H42: -17.13 | I42: -171.33 | J42: 171.33 | K42: -154.2 | L42: =IFERROR(ABS(K42),"") | M42: Amount Mismatch | N42: =IF(J42>Summary!$B$18,"Yes","No") | O42: =RANK(J42,$J$2:$J$64,0)
A43: TXN-00474 | B43: 45538 | C43: Office Supplies | D43: 6300 | E43: Printer consumables | F43: PRINTER CONSUMABLES | G43: -162.51 | H43: 138.6 | I43: -162.51 | J43: 162.51 | K43: -301.11 | L43: =IFERROR(ABS(K43),"") | M43: Amount Mismatch | N43: =IF(J43>Summary!$B$18,"Yes","No") | O43: =RANK(J43,$J$2:$J$64,0)
A44: TXN-09515 | B44: 45520 | C44: Unclassified (Bank only) | F44: ACCOUNT MAINTENANCE FE | H44: -141.9 | I44: -141.9 | J44: 141.9 | L44: =IFERROR(ABS(K44),"") | M44: Only in Bank | N44: =IF(J44>Summary!$B$18,"Yes","No") | O44: =RANK(J44,$J$2:$J$64,0)
A45: TXN-09502 | B45: 45604 | C45: Unclassified (Bank only) | F45: CARD PROCESSING FEE | H45: -131.58 | I45: -131.58 | J45: 131.58 | L45: =IFERROR(ABS(K45),"") | M45: Only in Bank | N45: =IF(J45>Summary!$B$18,"Yes","No") | O45: =RANK(J45,$J$2:$J$64,0)
A46: TXN-09506 | B46: 45421 | C46: Unclassified (Bank only) | F46: ACCOUNT MAINTENANCE FE | H46: -124.98 | I46: -124.98 | J46: 124.98 | L46: =IFERROR(ABS(K46),"") | M46: Only in Bank | N46: =IF(J46>Summary!$B$18,"Yes","No") | O46: =RANK(J46,$J$2:$J$64,0)
A47: TXN-09518 | B47: 45301 | C47: Unclassified (Bank only) | F47: ACCOUNT MAINTENANCE FE | H47: -123.28 | I47: -123.28 | J47: 123.28 | L47: =IFERROR(ABS(K47),"") | M47: Only in Bank | N47: =IF(J47>Summary!$B$18,"Yes","No") | O47: =RANK(J47,$J$2:$J$64,0)
A48: TXN-09520 | B48: 45576 | C48: Unclassified (Bank only) | F48: CARD PROCESSING FEE | H48: -121.39 | I48: -121.39 | J48: 121.39 | L48: =IFERROR(ABS(K48),"") | M48: Only in Bank | N48: =IF(J48>Summary!$B$18,"Yes","No") | O48: =RANK(J48,$J$2:$J$64,0)
A49: TXN-09501 | B49: 45439 | C49: Unclassified (Bank only) | F49: DEPOSIT INTEREST CREDI | H49: 112.9 | I49: 112.9 | J49: 112.9 | L49: =IFERROR(ABS(K49),"") | M49: Only in Bank | N49: =IF(J49>Summary!$B$18,"Yes","No") | O49: =RANK(J49,$J$2:$J$64,0)
A50: TXN-09510 | B50: 45364 | C50: Unclassified (Bank only) | F50: CARD PROCESSING FEE | H50: -109.88 | I50: -109.88 | J50: 109.88 | L50: =IFERROR(ABS(K50),"") | M50: Only in Bank | N50: =IF(J50>Summary!$B$18,"Yes","No") | O50: =RANK(J50,$J$2:$J$64,0)
A51: TXN-09503 | B51: 45506 | C51: Unclassified (Bank only) | F51: WIRE TRANSFER FEE | H51: -103.46 | I51: -103.46 | J51: 103.46 | L51: =IFERROR(ABS(K51),"") | M51: Only in Bank | N51: =IF(J51>Summary!$B$18,"Yes","No") | O51: =RANK(J51,$J$2:$J$64,0)
A52: TXN-09516 | B52: 45638 | C52: Unclassified (Bank only) | F52: SAVINGS INTEREST | H52: 97.76 | I52: 97.76 | J52: 97.76 | L52: =IFERROR(ABS(K52),"") | M52: Only in Bank | N52: =IF(J52>Summary!$B$18,"Yes","No") | O52: =RANK(J52,$J$2:$J$64,0)
A53: TXN-09505 | B53: 45506 | C53: Unclassified (Bank only) | F53: DEPOSIT INTEREST CREDI | H53: 92.59 | I53: 92.59 | J53: 92.59 | L53: =IFERROR(ABS(K53),"") | M53: Only in Bank | N53: =IF(J53>Summary!$B$18,"Yes","No") | O53: =RANK(J53,$J$2:$J$64,0)
A54: TXN-09511 | B54: 45527 | C54: Unclassified (Bank only) | F54: CARD PROCESSING FEE | H54: -80.36 | I54: -80.36 | J54: 80.36 | L54: =IFERROR(ABS(K54),"") | M54: Only in Bank | N54: =IF(J54>Summary!$B$18,"Yes","No") | O54: =RANK(J54,$J$2:$J$64,0)
A55: TXN-00579 | B55: 45299 | C55: Bank Fees | D55: 6900 | E55: Card processing fee | F55: CARD PROCESSING FEE | G55: -77.38 | H55: -773.8 | I55: -77.38 | J55: 77.38 | K55: 696.42 | L55: =IFERROR(ABS(K55),"") | M55: Amount Mismatch | N55: =IF(J55>Summary!$B$18,"Yes","No") | O55: =RANK(J55,$J$2:$J$64,0)
A56: TXN-09509 | B56: 45555 | C56: Unclassified (Bank only) | F56: WIRE TRANSFER FEE | H56: -69.71 | I56: -69.71 | J56: 69.71 | L56: =IFERROR(ABS(K56),"") | M56: Only in Bank | N56: =IF(J56>Summary!$B$18,"Yes","No") | O56: =RANK(J56,$J$2:$J$64,0)
A57: TXN-09513 | B57: 45582 | C57: Unclassified (Bank only) | F57: SAVINGS INTEREST | H57: 61.49 | I57: 61.49 | J57: 61.49 | L57: =IFERROR(ABS(K57),"") | M57: Only in Bank | N57: =IF(J57>Summary!$B$18,"Yes","No") | O57: =RANK(J57,$J$2:$J$64,0)
A58: TXN-09519 | B58: 45515 | C58: Unclassified (Bank only) | F58: WIRE TRANSFER FEE | H58: -60.58 | I58: -60.58 | J58: 60.58 | L58: =IFERROR(ABS(K58),"") | M58: Only in Bank | N58: =IF(J58>Summary!$B$18,"Yes","No") | O58: =RANK(J58,$J$2:$J$64,0)
A59: TXN-09514 | B59: 45586 | C59: Unclassified (Bank only) | F59: WIRE TRANSFER FEE | H59: -59.14 | I59: -59.14 | J59: 59.14 | L59: =IFERROR(ABS(K59),"") | M59: Only in Bank | N59: =IF(J59>Summary!$B$18,"Yes","No") | O59: =RANK(J59,$J$2:$J$64,0)
A60: TXN-09508 | B60: 45519 | C60: Unclassified (Bank only) | F60: CARD PROCESSING FEE | H60: -54.1 | I60: -54.1 | J60: 54.1 | L60: =IFERROR(ABS(K60),"") | M60: Only in Bank | N60: =IF(J60>Summary!$B$18,"Yes","No") | O60: =RANK(J60,$J$2:$J$64,0)
A61: TXN-00166 | B61: 45470 | C61: Bank Fees | D61: 6900 | E61: Account maintenance fee | F61: ACCOUNT MAINTENANCE FE | G61: -46.92 | H61: -469.2 | I61: -46.92 | J61: 46.92 | K61: 422.28 | L61: =IFERROR(ABS(K61),"") | M61: Amount Mismatch | N61: =IF(J61>Summary!$B$18,"Yes","No") | O61: =RANK(J61,$J$2:$J$64,0)
A62: TXN-09517 | B62: 45489 | C62: Unclassified (Bank only) | F62: SAVINGS INTEREST | H62: 46.77 | I62: 46.77 | J62: 46.77 | L62: =IFERROR(ABS(K62),"") | M62: Only in Bank | N62: =IF(J62>Summary!$B$18,"Yes","No") | O62: =RANK(J62,$J$2:$J$64,0)
A63: TXN-09512 | B63: 45396 | C63: Unclassified (Bank only) | F63: DEPOSIT INTEREST CREDI | H63: 24.9 | I63: 24.9 | J63: 24.9 | L63: =IFERROR(ABS(K63),"") | M63: Only in Bank | N63: =IF(J63>Summary!$B$18,"Yes","No") | O63: =RANK(J63,$J$2:$J$64,0)
A64: TXN-00829 | B64: 45404 | C64: Bank Fees | D64: 6900 | E64: Wire transfer fee | F64: WIRE TRANSFER FEE | G64: -13.53 | H64: 228.18 | I64: -13.53 | J64: 13.53 | K64: -241.71 | L64: =IFERROR(ABS(K64),"") | M64: Amount Mismatch | N64: =IF(J64>Summary!$B$18,"Yes","No") | O64: =RANK(J64,$J$2:$J$64,0)
A67: Kako se koristi ovaj sheet
A68: • Bijele kolone P (Assigned_To), Q (Resolution_Notes) i R (Resolved) su jedine za rucni unos — sve ostalo dolazi iz reconciliation-a ili je formula.
A69: • Primjer popunjenog reda: Assigned_To = "Ahmed H." | Resolution_Notes = "Kontaktirana banka, greska u unosu iznosa, ispravka knjizena 15.03." | Resolved = "Yes"
A70: • Kad upises "Yes" u kolonu R, cijeli red se oboji zeleno i vise ne trazi paznju.
A71: • Redovi su sortirani po Abs_Amount silazno — radi odozgo nadolje.
A72: • Kolona L (Abs_Diff) ima data bars: sve vrijednosti su pozitivne pa barovi krecu od lijeve ivice i duzina direktno znaci velicinu greske.
A73: • Above_Materiality (kolona N) poredi Abs_Amount sa pragom u Summary!B18.

Sheet Reconciliation
A1: Transaction_ID | B1: Date | C1: Month | D1: Category | E1: Account | F1: Description_GL | G1: Description_Bank | H1: Amount_GL | I1: Amount_Bank | J1: Amount | K1: Abs_Amount | L1: Amount_Diff | M1: Status | N1: Is_Exception | O1: Has_Duplicate_ID
A2: TXN-00001 | B2: 45326 | C2: 45323 | D2: Sales Revenue | E2: 4000 | F2: Customer deposit | G2: CUSTOMER DEPOSIT | H2: 6585.96 | I2: 6585.96 | J2: 6585.96 | K2: 6585.96 | M2: Matched | N2: No | O2: No
A3: TXN-00002 | B3: 45403 | C3: 45383 | D3: Marketing | E3: 6500 | F3: Trade fair booth | G3: TRADE FAIR BOOTH | H3: -2071.65 | I3: -2071.65 | J3: -2071.65 | K3: 2071.65 | M3: Matched | N3: No | O3: No
A4: TXN-00003 | B4: 45516 | C4: 45505 | D4: Rent | E4: 6100 | F4: Monthly office rent | G4: MONTHLY OFFICE RENT | H4: -5688.1 | I4: -5688.1 | J4: -5688.1 | K4: 5688.1 | M4: Matched | N4: No | O4: No
A5: TXN-00004 | B5: 45448 | C5: 45444 | D5: Office Supplies | E5: 6300 | F5: Stationery purchase | G5: STATIONERY PURCHASE | H5: -801.43 | I5: -801.43 | J5: -801.43 | K5: 801.43 | M5: Matched | N5: No | O5: No
A6: TXN-00005 | B6: 45578 | C6: 45566 | D6: Office Supplies | E6: 6300 | F6: Stationery purchase | G6: STATIONERY PURCHASE | H6: -475.54 | I6: -475.54 | J6: -475.54 | K6: 475.54 | M6: Matched | N6: No | O6: No
A7: TXN-00006 | B7: 45515 | C7: 45505 | D7: Bank Fees | E7: 6900 | F7: Card processing fee | G7: CARD PROCESSING FEE | H7: -76.14 | I7: -76.14 | J7: -76.14 | K7: 76.14 | M7: Matched | N7: No | O7: No
A8: TXN-00007 | B8: 45438 | C8: 45413 | D8: Sales Revenue | E8: 4000 | F8: Customer deposit | G8: CUSTOMER DEPOSIT | H8: 13645.92 | I8: 13645.92 | J8: 13645.92 | K8: 13645.92 | M8: Matched | N8: No | O8: No
A9: TXN-00008 | B9: 45523 | C9: 45505 | D9: Rent | E9: 6100 | F9: Warehouse lease | G9: WAREHOUSE LEASE | H9: -3059.73 | I9: -3059.73 | J9: -3059.73 | K9: 3059.73 | M9: Matched | N9: No | O9: No
A10: TXN-00009 | B10: 45646 | C10: 45627 | D10: Payroll | E10: 6000 | F10: Payroll transfer | G10: PAYROLL TRANSFER | H10: -2819.47 | I10: -2819.47 | J10: -2819.47 | K10: 2819.47 | M10: Matched | N10: No | O10: No
A11: TXN-00010 | B11: 45442 | C11: 45413 | D11: Sales Revenue | E11: 4000 | F11: Invoice payment received | G11: INVOICE PAYMENT RECEIV | H11: 23830.12 | I11: 23830.12 | J11: 23830.12 | K11: 23830.12 | M11: Matched | N11: No | O11: No
A12: TXN-00011 | B12: 45348 | C12: 45323 | D12: Travel & Entertainment | E12: 6400 | F12: Business trip - airfare | G12: BUSINESS TRIP - AIRFAR | H12: -3339.96 | I12: -3339.96 | J12: -3339.96 | K12: 3339.96 | M12: Matched | N12: No | O12: No
A13: TXN-00012 | B13: 45441 | C13: 45413 | D13: Interest Income | E13: 4900 | F13: Savings interest | G13: SAVINGS INTEREST | H13: 69.61 | I13: 69.61 | J13: 69.61 | K13: 69.61 | M13: Matched | N13: No | O13: No
... A120: TXN-00119 | B120: 45413 | C120: 45413 | D120: Payroll | E120: 6000 | F120: Monthly salary run | G120: MONTHLY SALARY RUN | H120: -8353.21 | I120: -8353.21 | J120: -8353.21 | K120: 8353.21 | M120: Matched | N120: No | O120: No
A121: TXN-00120 | B121: 45295 | C121: 45292 | D121: Vendor Payment | E121: 5100 | F121: Contractor fee | G121: CONTRACTOR FEE | H121: -14882.22 | I121: -148822.2 | J121: -14882.22 | K121: 14882.22 | L121: 133939.98 | M121: Amount Mismatch | N121: Yes | O121: No
A122: TXN-00121 | B122: 45538 | C122: 45536 | D122: Office Supplies | E122: 6300 | F122: Stationery purchase | G122: STATIONERY PURCHASE | H122: -474.48 | I122: -474.48 | J122: -474.48 | K122: 474.48 | M122: Matched | N122: No | O122: No
A123: TXN-00122 | B123: 45368 | C123: 45352 | D123: Rent | E123: 6100 | F123: Rent payment | G123: RENT PAYMENT | H123: -1295.04 | I123: -1295.04 | J123: -1295.04 | K123: 1295.04 | M123: Matched | N123: No | O123: No
A124: TXN-00123 | B124: 45568 | C124: 45566 | D124: Rent | E124: 6100 | F124: Rent payment | G124: RENT PAYMENT | H124: -5878.65 | I124: -5878.65 | J124: -5878.65 | K124: 5878.65 | M124: Matched | N124: No | O124: No
A125: TXN-00124 | B125: 45483 | C125: 45474 | D125: Office Supplies | E125: 6300 | F125: Office equipment | G125: OFFICE EQUIPMENT | H125: -300.13 | I125: -300.13 | J125: -300.13 | K125: 300.13 | M125: Matched | N125: No | O125: No
A126: TXN-00125 | B126: 45462 | C126: 45444 | D126: Bank Fees | E126: 6900 | F126: Account maintenance fee | G126: ACCOUNT MAINTENANCE FE | H126: -66.59 | I126: -66.59 | J126: -66.59 | K126: 66.59 | M126: Matched | N126: No | O126: No
A127: TXN-00126 | B127: 45351 | C127: 45323 | D127: Travel & Entertainment | E127: 6400 | F127: Client dinner | G127: CLIENT DINNER | H127: -255.85 | I127: -255.85 | J127: -255.85 | K127: 255.85 | M127: Matched | N127: No | O127: No
A128: TXN-00127 | B128: 45551 | C128: 45536 | D128: Sales Revenue | E128: 4000 | F128: Customer deposit | G128: CUSTOMER DEPOSIT | H128: 9156.77 | I128: 9156.77 | J128: 9156.77 | K128: 9156.77 | M128: Matched | N128: No | O128: No
A129: TXN-00128 | B129: 45352 | C129: 45352 | D129: Marketing | E129: 6500 | F129: Print advertising | G129: PRINT ADVERTISING | H129: -6331.59 | I129: -6331.59 | J129: -6331.59 | K129: 6331.59 | M129: Matched | N129: No | O129: No
A130: TXN-00129 | B130: 45444 | C130: 45444 | D130: Travel & Entertainment | E130: 6400 | F130: Hotel accommodation | G130: HOTEL ACCOMMODATION | H130: -2888.61 | I130: -2888.61 | J130: -2888.61 | K130: 2888.61 | M130: Matched | N130: No | O130: No
A131: TXN-00130 | B131: 45597 | C131: 45597 | D131: Rent | E131: 6100 | F131: Rent payment | G131: RENT PAYMENT | H131: -2966.66 | I131: -2966.66 | J131: -2966.66 | K131: 2966.66 | M131: Matched | N131: No | O131: No
A132: TXN-00131 | B132: 45627 | C132: 45627 | D132: Travel & Entertainment | E132: 6400 | F132: Client dinner | G132: CLIENT DINNER | H132: -2640.97 | I132: -2640.97 | J132: -2640.97 | K132: 2640.97 | M132: Matched | N132: No | O132: No
A133: TXN-00132 | B133: 45653 | C133: 45627 | D133: Travel & Entertainment | E133: 6400 | F133: Business trip - airfare | G133: BUSINESS TRIP - AIRFAR | H133: -2820.75 | I133: -2820.75 | J133: -2820.75 | K133: 2820.75 | M133: Matched | N133: No | O133: No
... A166: TXN-00165 | B166: 45362 | C166: 45352 | D166: Office Supplies | E166: 6300 | F166: Printer consumables | G166: PRINTER CONSUMABLES | H166: -597.35 | I166: -597.35 | J166: -597.35 | K166: 597.35 | M166: Matched | N166: No | O166: No
A167: TXN-00166 | B167: 45470 | C167: 45444 | D167: Bank Fees | E167: 6900 | F167: Account maintenance fee | G167: ACCOUNT MAINTENANCE FE | H167: -46.92 | I167: -469.2 | J167: -46.92 | K167: 46.92 | L167: 422.28 | M167: Amount Mismatch | N167: Yes | O167: No
A168: TXN-00167 | B168: 45655 | C168: 45627 | D168: Utilities | E168: 6200 | F168: Electricity bill | G168: ELECTRICITY BILL | H168: -701.38 | I168: -701.38 | J168: -701.38 | K168: 701.38 | M168: Matched | N168: No | O168: No
A169: TXN-00168 | B169: 45506 | C169: 45505 | D169: Vendor Payment | E169: 5100 | F169: Contractor fee | G169: CONTRACTOR FEE | H169: -8353.45 | I169: -8353.45 | J169: -8353.45 | K169: 8353.45 | M169: Matched | N169: No | O169: No
A170: TXN-00169 | B170: 45555 | C170: 45536 | D170: Utilities | E170: 6200 | F170: Water utility | G170: WATER UTILITY | H170: -867.11 | I170: -867.11 | J170: -867.11 | K170: 867.11 | M170: Matched | N170: No | O170: No
A171: TXN-00170 | B171: 45472 | C171: 45444 | D171: Sales Revenue | E171: 4000 | F171: Product sale | G171: PRODUCT SALE | H171: 1151.16 | I171: 1151.16 | J171: 1151.16 | K171: 1151.16 | M171: Matched | N171: No | O171: No
A172: TXN-00171 | B172: 45297 | C172: 45292 | D172: Vendor Payment | E172: 5100 | F172: Vendor payment - materials | G172: VENDOR PAYMENT - MATER | H172: -9103.07 | I172: -9103.07 | J172: -9103.07 | K172: 9103.07 | M172: Matched | N172: No | O172: No
A173: TXN-00172 | B173: 45322 | C173: 45292 | D173: Sales Revenue | E173: 4000 | F173: Invoice payment received | G173: INVOICE PAYMENT RECEIV | H173: 12411.71 | I173: 12411.71 | J173: 12411.71 | K173: 12411.71 | M173: Matched | N173: No | O173: No
A174: TXN-00173 | B174: 45390 | C174: 45383 | D174: Marketing | E174: 6500 | F174: Trade fair booth | G174: TRADE FAIR BOOTH | H174: -3436.45 | I174: -3436.45 | J174: -3436.45 | K174: 3436.45 | M174: Matched | N174: No | O174: No
A175: TXN-00174 | B175: 45380 | C175: 45352 | D175: Marketing | E175: 6500 | F175: Online ad campaign | G175: ONLINE AD CAMPAIGN | H175: -6099.6 | I175: -6099.6 | J175: -6099.6 | K175: 6099.6 | M175: Matched | N175: No | O175: No
A176: TXN-00175 | B176: 45598 | C176: 45597 | D176: Rent | E176: 6100 | F176: Monthly office rent | G176: MONTHLY OFFICE RENT | H176: -3718.36 | I176: -3718.36 | J176: -3718.36 | K176: 3718.36 | M176: Matched | N176: No | O176: No
A177: TXN-00176 | B177: 45599 | C177: 45597 | D177: Office Supplies | E177: 6300 | F177: Office equipment | G177: OFFICE EQUIPMENT | H177: -359.13 | I177: -359.13 | J177: -359.13 | K177: 359.13 | M177: Matched | N177: No | O177: No
A178: TXN-00177 | B178: 45603 | C178: 45597 | D178: Marketing | E178: 6500 | F178: Print advertising | G178: PRINT ADVERTISING | H178: -4247.06 | I178: -4247.06 | J178: -4247.06 | K178: 4247.06 | M178: Matched | N178: No | O178: No
A179: TXN-00178 | B179: 45524 | C179: 45505 | D179: Vendor Payment | E179: 5100 | F179: Supplier invoice | G179: SUPPLIER INVOICE | H179: -4858.29 | I179: -4858.29 | J179: -4858.29 | K179: 4858.29 | M179: Matched | N179: No | O179: No
... A183: TXN-00182 | B183: 45536 | C183: 45536 | D183: Vendor Payment | E183: 5100 | F183: Supplier invoice | G183: SUPPLIER INVOICE | H183: -13438.77 | I183: -13438.77 | J183: -13438.77 | K183: 13438.77 | M183: Matched | N183: No | O183: No
A184: TXN-00183 | B184: 45581 | C184: 45566 | D184: Office Supplies | E184: 6300 | F184: Office equipment | G184: OFFICE EQUIPMENT | H184: -171.33 | I184: -17.13 | J184: -171.33 | K184: 171.33 | L184: -154.2 | M184: Amount Mismatch | N184: Yes | O184: No
A185: TXN-00184 | B185: 45570 | C185: 45566 | D185: Rent | E185: 6100 | F185: Warehouse lease | G185: WAREHOUSE LEASE | H185: -5429.37 | I185: -5429.37 | J185: -5429.37 | K185: 5429.37 | M185: Matched | N185: No | O185: No
A186: TXN-00185 | B186: 45516 | C186: 45505 | D186: Office Supplies | E186: 6300 | F186: Stationery purchase | G186: STATIONERY PURCHASE | H186: -438.96 | I186: -438.96 | J186: -438.96 | K186: 438.96 | M186: Matched | N186: No | O186: No
A187: TXN-00186 | B187: 45313 | C187: 45292 | D187: Office Supplies | E187: 6300 | F187: Printer consumables | G187: PRINTER CONSUMABLES | H187: -843.28 | I187: -843.28 | J187: -843.28 | K187: 843.28 | M187: Matched | N187: No | O187: No
A188: TXN-00187 | B188: 45556 | C188: 45536 | D188: Vendor Payment | E188: 5100 | F188: Vendor payment - materials | G188: VENDOR PAYMENT - MATER | H188: -3384.64 | I188: -3384.64 | J188: -3384.64 | K188: 3384.64 | M188: Matched | N188: No | O188: No
A189: TXN-00188 | B189: 45425 | C189: 45413 | D189: Utilities | E189: 6200 | F189: Electricity bill | G189: ELECTRICITY BILL | H189: -723.64 | I189: -723.64 | J189: -723.64 | K189: 723.64 | M189: Matched | N189: No | O189: No
A190: TXN-00189 | B190: 45563 | C190: 45536 | D190: Payroll | E190: 6000 | F190: Payroll transfer | G190: PAYROLL TRANSFER | H190: -8635.03 | I190: -8635.03 | J190: -8635.03 | K190: 8635.03 | M190: Matched | N190: No | O190: No
A191: TXN-00190 | B191: 45488 | C191: 45474 | D191: Utilities | E191: 6200 | F191: Electricity bill | G191: ELECTRICITY BILL | H191: -296.21 | I191: -296.21 | J191: -296.21 | K191: 296.21 | M191: Matched | N191: No | O191: No
A192: TXN-00191 | B192: 45613 | C192: 45597 | D192: Rent | E192: 6100 | F192: Rent payment | G192: RENT PAYMENT | H192: -1876.32 | I192: -1876.32 | J192: -1876.32 | K192: 1876.32 | M192: Matched | N192: No | O192: No
A193: TXN-00192 | B193: 45415 | C193: 45413 | D193: Rent | E193: 6100 | F193: Monthly office rent | G193: MONTHLY OFFICE RENT | H193: -2998.22 | I193: -2998.22 | J193: -2998.22 | K193: 2998.22 | M193: Matched | N193: No | O193: No
A194: TXN-00193 | B194: 45631 | C194: 45627 | D194: Rent | E194: 6100 | F194: Warehouse lease | G194: WAREHOUSE LEASE | H194: -1500.4 | I194: -1500.4 | J194: -1500.4 | K194: 1500.4 | M194: Matched | N194: No | O194: No
A195: TXN-00194 | B195: 45600 | C195: 45597 | D195: Utilities | E195: 6200 | F195: Electricity bill | G195: ELECTRICITY BILL | H195: -1039.32 | I195: -1039.32 | J195: -1039.32 | K195: 1039.32 | M195: Matched | N195: No | O195: No
A196: TXN-00195 | B196: 45412 | C196: 45383 | D196: Interest Income | E196: 4900 | F196: Deposit interest credit | G196: DEPOSIT INTEREST CREDI | H196: 147.5 | I196: 147.5 | J196: 147.5 | K196: 147.5 | M196: Matched | N196: No | O196: No
... A206: TXN-00205 | B206: 45403 | C206: 45383 | D206: Office Supplies | E206: 6300 | F206: Office equipment | G206: OFFICE EQUIPMENT | H206: -741.43 | I206: -741.43 | J206: -741.43 | K206: 741.43 | M206: Matched | N206: No | O206: No
A207: TXN-00206 | B207: 45506 | C207: 45505 | D207: Payroll | E207: 6000 | F207: Employee wages | G207: EMPLOYEE WAGES | H207: -7023.64 | I207: -70.23 | J207: -7023.64 | K207: 7023.64 | L207: -6953.41 | M207: Amount Mismatch | N207: Yes | O207: No
A208: TXN-00207 | B208: 45335 | C208: 45323 | D208: Marketing | E208: 6500 | F208: Online ad campaign | G208: ONLINE AD CAMPAIGN | H208: -496.77 | I208: -496.77 | J208: -496.77 | K208: 496.77 | M208: Matched | N208: No | O208: No
A209: TXN-00208 | B209: 45602 | C209: 45597 | D209: Interest Income | E209: 4900 | F209: Interest accrual | G209: INTEREST ACCRUAL | H209: 163.5 | I209: 163.5 | J209: 163.5 | K209: 163.5 | M209: Matched | N209: No | O209: No
A210: TXN-00209 | B210: 45432 | C210: 45413 | D210: Payroll | E210: 6000 | F210: Monthly salary run | G210: MONTHLY SALARY RUN | H210: -11460.78 | I210: -11460.78 | J210: -11460.78 | K210: 11460.78 | M210: Matched | N210: No | O210: No
A211: TXN-00210 | B211: 45416 | C211: 45413 | D211: Marketing | E211: 6500 | F211: Online ad campaign | G211: ONLINE AD CAMPAIGN | H211: -4678.36 | I211: -4678.36 | J211: -4678.36 | K211: 4678.36 | M211: Matched | N211: No | O211: No
A212: TXN-00211 | B212: 45504 | C212: 45474 | D212: Payroll | E212: 6000 | F212: Employee wages | G212: EMPLOYEE WAGES | H212: -3288.58 | I212: -3288.58 | J212: -3288.58 | K212: 3288.58 | M212: Matched | N212: No | O212: No
A213: TXN-00212 | B213: 45474 | C213: 45474 | D213: Marketing | E213: 6500 | F213: Print advertising | G213: PRINT ADVERTISING | H213: -7832.28 | I213: -7832.28 | J213: -7832.28 | K213: 7832.28 | M213: Matched | N213: No | O213: No
A214: TXN-00213 | B214: 45601 | C214: 45597 | D214: Marketing | E214: 6500 | F214: Online ad campaign | G214: ONLINE AD CAMPAIGN | H214: -4025.33 | I214: -4025.33 | J214: -4025.33 | K214: 4025.33 | M214: Matched | N214: No | O214: No
A215: TXN-00214 | B215: 45485 | C215: 45474 | D215: Office Supplies | E215: 6300 | F215: Printer consumables | G215: PRINTER CONSUMABLES | H215: -874.38 | I215: -874.38 | J215: -874.38 | K215: 874.38 | M215: Matched | N215: No | O215: No
A216: TXN-00215 | B216: 45480 | C216: 45474 | D216: Marketing | E216: 6500 | F216: Print advertising | G216: PRINT ADVERTISING | H216: -3270.57 | I216: -3270.57 | J216: -3270.57 | K216: 3270.57 | M216: Matched | N216: No | O216: No
A217: TXN-00216 | B217: 45330 | C217: 45323 | D217: Payroll | E217: 6000 | F217: Payroll transfer | G217: PAYROLL TRANSFER | H217: -7639.9 | I217: -7639.9 | J217: -7639.9 | K217: 7639.9 | M217: Matched | N217: No | O217: No
A218: TXN-00217 | B218: 45300 | C218: 45292 | D218: Sales Revenue | E218: 4000 | F218: Customer deposit | G218: CUSTOMER DEPOSIT | H218: 8366.6 | I218: 8366.6 | J218: 8366.6 | K218: 8366.6 | M218: Matched | N218: No | O218: No
A219: TXN-00218 | B219: 45437 | C219: 45413 | D219: Sales Revenue | E219: 4000 | F219: Invoice payment received | G219: INVOICE PAYMENT RECEIV | H219: 5233.6 | I219: 5233.6 | J219: 5233.6 | K219: 5233.6 | M219: Matched | N219: No | O219: No
... A245: TXN-00244 | B245: 45548 | C245: 45536 | D245: Rent | E245: 6100 | F245: Monthly office rent | G245: MONTHLY OFFICE RENT | H245: -4338.18 | I245: -4338.18 | J245: -4338.18 | K245: 4338.18 | M245: Matched | N245: No | O245: No
A246: TXN-00245 | B246: 45483 | C246: 45474 | D246: Rent | E246: 6100 | F246: Rent payment | G246: RENT PAYMENT | H246: -937.97 | I246: -93.79 | J246: -937.97 | K246: 937.97 | L246: -844.18 | M246: Amount Mismatch | N246: Yes | O246: No
A247: TXN-00246 | B247: 45523 | C247: 45505 | D247: Sales Revenue | E247: 4000 | F247: Customer deposit | G247: CUSTOMER DEPOSIT | H247: 18714.77 | I247: 18714.77 | J247: 18714.77 | K247: 18714.77 | M247: Matched | N247: No | O247: No
A248: TXN-00247 | B248: 45552 | C248: 45536 | D248: Marketing | E248: 6500 | F248: Online ad campaign | G248: ONLINE AD CAMPAIGN | H248: -4046.88 | I248: -4046.88 | J248: -4046.88 | K248: 4046.88 | M248: Matched | N248: No | O248: No
A249: TXN-00248 | B249: 45650 | C249: 45627 | D249: Office Supplies | E249: 6300 | F249: Office equipment | G249: OFFICE EQUIPMENT | H249: -429.87 | I249: -429.87 | J249: -429.87 | K249: 429.87 | M249: Matched | N249: No | O249: No
A250: TXN-00249 | B250: 45585 | C250: 45566 | D250: Marketing | E250: 6500 | F250: Trade fair booth | G250: TRADE FAIR BOOTH | H250: -6325.2 | I250: -6325.2 | J250: -6325.2 | K250: 6325.2 | M250: Matched | N250: No | O250: No
A251: TXN-00250 | B251: 45518 | C251: 45505 | D251: Sales Revenue | E251: 4000 | F251: Invoice payment received | G251: INVOICE PAYMENT RECEIV | H251: 8602.54 | I251: 8602.54 | J251: 8602.54 | K251: 8602.54 | M251: Matched | N251: No | O251: No
A252: TXN-00251 | B252: 45612 | C252: 45597 | D252: Vendor Payment | E252: 5100 | F252: Contractor fee | G252: CONTRACTOR FEE | H252: -5721.3 | I252: -5721.3 | J252: -5721.3 | K252: 5721.3 | M252: Matched | N252: No | O252: No
A253: TXN-00252 | B253: 45466 | C253: 45444 | D253: Office Supplies | E253: 6300 | F253: Office equipment | G253: OFFICE EQUIPMENT | H253: -517.27 | I253: -517.27 | J253: -517.27 | K253: 517.27 | M253: Matched | N253: No | O253: No
A254: TXN-00253 | B254: 45651 | C254: 45627 | D254: Vendor Payment | E254: 5100 | F254: Supplier invoice | G254: SUPPLIER INVOICE | H254: -2576.71 | I254: -2576.71 | J254: -2576.71 | K254: 2576.71 | M254: Matched | N254: No | O254: No
A255: TXN-00254 | B255: 45569 | C255: 45566 | D255: Utilities | E255: 6200 | F255: Electricity bill | G255: ELECTRICITY BILL | H255: -941.14 | I255: -941.14 | J255: -941.14 | K255: 941.14 | M255: Matched | N255: No | O255: No
A256: TXN-00255 | B256: 45529 | C256: 45505 | D256: Rent | E256: 6100 | F256: Monthly office rent | G256: MONTHLY OFFICE RENT | H256: -3589.74 | I256: -3589.74 | J256: -3589.74 | K256: 3589.74 | M256: Matched | N256: No | O256: No
A257: TXN-00256 | B257: 45621 | C257: 45597 | D257: Vendor Payment | E257: 5100 | F257: Vendor payment - materials | G257: VENDOR PAYMENT - MATER | H257: -14488.16 | I257: -14488.16 | J257: -14488.16 | K257: 14488.16 | M257: Matched | N257: No | O257: No
A258: TXN-00257 | B258: 45480 | C258: 45474 | D258: Rent | E258: 6100 | F258: Monthly office rent | G258: MONTHLY OFFICE RENT | H258: -5249.34 | I258: -5249.34 | J258: -5249.34 | K258: 5249.34 | M258: Matched | N258: No | O258: No
... A376: TXN-00375 | B376: 45608 | C376: 45597 | D376: Bank Fees | E376: 6900 | F376: Wire transfer fee | G376: WIRE TRANSFER FEE | H376: -95.89 | I376: -95.89 | J376: -95.89 | K376: 95.89 | M376: Matched | N376: No | O376: No
A377: TXN-00376 | B377: 45360 | C377: 45352 | D377: Sales Revenue | E377: 4000 | F377: Invoice payment received | G377: INVOICE PAYMENT RECEIV | H377: 18808.11 | I377: 188081.1 | J377: 18808.11 | K377: 18808.11 | L377: -169272.99 | M377: Amount Mismatch | N377: Yes | O377: No
A378: TXN-00377 | B378: 45539 | C378: 45536 | D378: Marketing | E378: 6500 | F378: Online ad campaign | G378: ONLINE AD CAMPAIGN | H378: -2289.8 | I378: -2289.8 | J378: -2289.8 | K378: 2289.8 | M378: Matched | N378: No | O378: No
A379: TXN-00378 | B379: 45322 | C379: 45292 | D379: Marketing | E379: 6500 | F379: Print advertising | G379: PRINT ADVERTISING | H379: -1019.19 | I379: -1019.19 | J379: -1019.19 | K379: 1019.19 | M379: Matched | N379: No | O379: No
A380: TXN-00379 | B380: 45538 | C380: 45536 | D380: Utilities | E380: 6200 | F380: Electricity bill | G380: ELECTRICITY BILL | H380: -227.59 | I380: -227.59 | J380: -227.59 | K380: 227.59 | M380: Matched | N380: No | O380: No
A381: TXN-00380 | B381: 45416 | C381: 45413 | D381: Payroll | E381: 6000 | F381: Employee wages | G381: EMPLOYEE WAGES | H381: -3575.5 | I381: -3575.5 | J381: -3575.5 | K381: 3575.5 | M381: Matched | N381: No | O381: No
A382: TXN-00381 | B382: 45456 | C382: 45444 | D382: Sales Revenue | E382: 4000 | F382: Customer deposit | G382: CUSTOMER DEPOSIT | H382: 13470.09 | I382: 13470.09 | J382: 13470.09 | K382: 13470.09 | M382: Matched | N382: No | O382: No
A383: TXN-00382 | B383: 45553 | C383: 45536 | D383: Interest Income | E383: 4900 | F383: Deposit interest credit | G383: DEPOSIT INTEREST CREDI | H383: 353.72 | I383: 353.72 | J383: 353.72 | K383: 353.72 | M383: Matched | N383: No | O383: No
A384: TXN-00383 | B384: 45447 | C384: 45444 | D384: Interest Income | E384: 4900 | F384: Interest accrual | G384: INTEREST ACCRUAL | H384: 284.72 | I384: 284.72 | J384: 284.72 | K384: 284.72 | M384: Matched | N384: No | O384: No
A385: TXN-00384 | B385: 45586 | C385: 45566 | D385: Payroll | E385: 6000 | F385: Employee wages | G385: EMPLOYEE WAGES | H385: -3339.4 | I385: -3339.4 | J385: -3339.4 | K385: 3339.4 | M385: Matched | N385: No | O385: No
A386: TXN-00385 | B386: 45486 | C386: 45474 | D386: Sales Revenue | E386: 4000 | F386: Product sale | G386: PRODUCT SALE | H386: 12220.92 | I386: 12220.92 | J386: 12220.92 | K386: 12220.92 | M386: Matched | N386: No | O386: No
A387: TXN-00386 | B387: 45656 | C387: 45627 | D387: Vendor Payment | E387: 5100 | F387: Vendor payment - materials | G387: VENDOR PAYMENT - MATER | H387: -2381.9 | I387: -2381.9 | J387: -2381.9 | K387: 2381.9 | M387: Matched | N387: No | O387: No
A388: TXN-00387 | B388: 45524 | C388: 45505 | D388: Sales Revenue | E388: 4000 | F388: Customer deposit | G388: CUSTOMER DEPOSIT | H388: 8054.16 | I388: 8054.16 | J388: 8054.16 | K388: 8054.16 | M388: Matched | N388: No | O388: No
A389: TXN-00388 | B389: 45400 | C389: 45383 | D389: Bank Fees | E389: 6900 | F389: Account maintenance fee | G389: ACCOUNT MAINTENANCE FE | H389: -23.46 | I389: -23.46 | J389: -23.46 | K389: 23.46 | M389: Matched | N389: No | O389: No
... A474: TXN-00473 | B474: 45506 | C474: 45505 | D474: Office Supplies | E474: 6300 | F474: Printer consumables | G474: PRINTER CONSUMABLES | H474: -50.9 | I474: -50.9 | J474: -50.9 | K474: 50.9 | M474: Matched | N474: No | O474: No
A475: TXN-00474 | B475: 45538 | C475: 45536 | D475: Office Supplies | E475: 6300 | F475: Printer consumables | G475: PRINTER CONSUMABLES | H475: -162.51 | I475: 138.6 | J475: -162.51 | K475: 162.51 | L475: -301.11 | M475: Amount Mismatch | N475: Yes | O475: No
A476: TXN-00475 | B476: 45385 | C476: 45383 | D476: Rent | E476: 6100 | F476: Rent payment | G476: RENT PAYMENT | H476: -4871.11 | I476: -4871.11 | J476: -4871.11 | K476: 4871.11 | M476: Matched | N476: No | O476: No
...

Sheet GL_Data
A1: Transaction_ID | B1: Date | C1: Description | D1: Category | E1: Amount | F1: Account | G1: Is_Duplicate
A2: TXN-00458 | B2: 45611 | C2: Rent payment | D2: Rent | E2: -2897.44 | F2: 6100 | G2: No
A3: TXN-00930 | B3: 45328 | C3: Hotel accommodation | D3: Travel & Entertainment | E3: -2555.21 | F3: 6400 | G3: No
A4: TXN-00330 | B4: 45607 | C4: Business trip - airfare | D4: Travel & Entertainment | E4: -747.32 | F4: 6400 | G4: No
A5: TXN-00350 | B5: 45302 | C5: Supplier invoice | D5: Vendor Payment | E5: -7889.33 | F5: 5100 | G5: No
A6: TXN-00784 | B6: 45607 | C6: Supplier invoice | D6: Vendor Payment | E6: -5900.48 | F6: 5100 | G6: No
A7: TXN-00134 | B7: 45494 | C7: Client dinner | D7: Travel & Entertainment | E7: -572.17 | F7: 6400 | G7: No
A8: TXN-00121 | B8: 45538 | C8: Stationery purchase | D8: Office Supplies | E8: -474.48 | F8: 6300 | G8: No
A9: TXN-00436 | B9: 45377 | C9: Supplier invoice | D9: Vendor Payment | E9: -12254.21 | F9: 5100 | G9: No
A10: TXN-00095 | B10: 45550 | C10: Wire transfer fee | D10: Bank Fees | E10: -46.95 | F10: 6900 | G10: No
A11: TXN-00763 | B11: 45613 | C11: Deposit interest credit | D11: Interest Income | E11: 360.54 | F11: 4900 | G11: No
A12: TXN-00456 | B12: 45348 | C12: Hotel accommodation | D12: Travel & Entertainment | E12: -2441.17 | F12: 6400 | G12: No
A13: TXN-00007 | B13: 45438 | C13: Customer deposit | D13: Sales Revenue | E13: 13645.92 | F13: 4000 | G13: No
... A982: TXN-00038 | B982: 45407 | C982: Wire transfer fee | D982: Bank Fees | E982: -138.67 | F982: 6900 | G982: No

Sheet Bank_Data
A1: Transaction_ID | B1: Date | C1: Description | D1: Amount | E1: Is_Duplicate
A2: TXN-00609 | B2: 45655 | C2: DEPOSIT INTEREST CREDI | D2: 213.08 | E2: No
A3: TXN-00398 | B3: 45548 | C3: VENDOR PAYMENT - MATER | D3: -3765.72 | E3: No
A4: TXN-00776 | B4: 45580 | C4: SAVINGS INTEREST | D4: 247.18 | E4: No
A5: TXN-00415 | B5: 45497 | C5: CUSTOMER DEPOSIT | D5: 14027.99 | E5: No
A6: TXN-00198 | B6: 45575 | C6: VENDOR PAYMENT - MATER | D6: -9235.18 | E6: No
A7: TXN-00526 | B7: 45405 | C7: INTERNET & TELECOM | D7: -660.99 | E7: No
A8: TXN-00766 | B8: 45615 | C8: ONLINE AD CAMPAIGN | D8: -1122.91 | E8: No
A9: TXN-00228 | B9: 45364 | C9: CLIENT DINNER | D9: -2332.94 | E9: No
A10: TXN-00820 | B10: 45364 | C10: INTEREST ACCRUAL | D10: 388.06 | E10: No
A11: TXN-00578 | B11: 45344 | C11: HOTEL ACCOMMODATION | D11: -2680.64 | E11: No
A12: TXN-00346 | B12: 45480 | C12: PAYROLL TRANSFER | D12: -9080.02 | E12: No
A13: TXN-00791 | B13: 45451 | C13: PRODUCT SALE | D13: 8207.25 | E13: No
... A975: TXN-00169 | B975: 45557 | C975: WATER UTILITY | D975: -867.11 | E975: No

Sheet Sheet1
A3: Row Labels | B3: Count of Transaction_ID | C3: Count of Transaction_ID2
A4: Matched | B4: 932 | C4: 0.93668342
A5: Only in GL | B5: 25 | C5: 0.025125628
A6: Only in Bank | B6: 20 | C6: 0.020100503
A7: Amount Mismatch | B7: 18 | C7: 0.018090452
A8: Grand Total | B8: 995 | C8: 1
A27: Sum of Abs_Amount | B27: Column Labels
A28: Row Labels | B28: No | C28: Yes | D28: Grand Total
A29: Sales Revenue | B29: 1078173.6 | C29: 18808.11 | D29: 1096981.7
A30: Vendor Payment | B30: 822259.99 | C30: 153310.68 | D30: 975570.67
A31: Payroll | B31: 532843.89 | C31: 46445.12 | D31: 579289.01
A32: Marketing | B32: 424140.85 | D32: 424140.85
A33: Rent | B33: 309720.48 | C33: 34196.69 | D33: 343917.17
A34: Travel & Entertainment | B34: 170228.14 | C34: 3989.45 | D34: 174217.59
A35: Office Supplies | B35: 52095.91 | C35: 1154.46 | D35: 53250.37
A36: Utilities | B36: 41177.74 | C36: 747.51 | D36: 41925.25
A37: Interest Income | B37: 21137.26 | D37: 21137.26
A38: Bank Fees | B38: 6585.07 | C38: 137.83 | D38: 6722.9
A39: Unclassified (Bank only) | C39: 2095.14 | D39: 2095.14
A40: Grand Total | B40: 3458362.9 | C40: 260884.99 | D40: 3719247.9
A47: Is_Exception | B47: Yes
A49: Row Labels | B49: Count of Transaction_ID
A50: 45292 | B50: 7
A51: 45323 | B51: 2
A52: 45352 | B52: 4
A53: 45383 | B53: 5
A54: 45413 | B54: 7
A55: 45444 | B55: 2
A56: 45474 | B56: 7
A57: 45505 | B57: 10
A58: 45536 | B58: 4
A59: 45566 | B59: 6
A60: 45597 | B60: 4
A61: 45627 | B61: 5
A62: Grand Total | B62: 63
